# This file is optional and here as an example of how to activate the build runner
# FEEL FREE TO DELETE!!

# Save the game opening and result to disk?
# Setting to `True` allows Ares to select a new opening after defeat
UseData: True
# How should we choose a build? Cycle is the only option for now
BuildSelection: Cycle
# For each Race / Opponent ID choose a build selection
BuildChoices:
    # test_123 is active if Debug: True (set via a `config.yml` file)
    test_123:
        BotName: Test
        Cycle:
            - OneOneRoaches

    Protoss:
        BotName: ProtossRace
        Cycle:
            - HatcheryFirst

    Random:
        BotName: RandomRace
        Cycle:
            - Standard

    Terran:
        BotName: TerranRace
        Cycle:
            - MacroVsTerran

    Zerg:
        BotName: ZergRace
        Cycle:
            - OneOneRoaches

    # Can also use specific opponent ids (overrides race options above)
    #a_bot_opponent_id_from_aiarena:
    #    BotName: QueenBot
    #    Cycle:
    #        - DummyOpening



    c033a97a-667d-42e3-91e8-13528ac191ed:
        BotName: Apidae
        Cycle:
            - TwelvePool


    4a491758-76ff-40de-996c-018d49b6237f:
        BotName: 12PoolBot
        Cycle:
            - OppeningVsLingRush

    81654bce-d0ae-4456-b987-2b585fe5a819:
        BotName: Tartarus
        Cycle:
            - OppeningVsLingRush


    a51d7f01-0f4a-4b91-ada8-7bd1eeec2cda:
        BotName: Krillin
        Cycle:
            - OppeningVsLingRush


    8ac35b6f-7a16-4a4d-a69e-4f84d92b18c4:
        BotName: EvilKinGG
        Cycle:
            - OppeningVsLingRush

    c121cc44-2b7e-4523-b950-d9fbff506255:
        BotName: BrazilianLingFloodBot
        Cycle:
            - OppeningVsLingRush

    88b7a15a-b346-4426-9103-094a260b873c:
        BotName: shyguy
        Cycle:
            - OppeningVsMarineRush





Builds:
    BurrowRoachRush:
        # Build constant workers till x supply
        # Turning this off here for a bit more precision in build
        ConstantWorkerProductionTill: 0
        OpeningBuildOrder:
            - 12 drone
            - 13 drone
            - 14 spawningpool
            - 13 drone
            - 14 hatchery
            - 13 overlord
            - 13 drone
            - 14 drone
            - 16 queen
            - 16 gas
            - 14 drone
            - 14 drone
            - 15 drone
            - 15 drone
            - 15 drone
            - 15 drone
            - 15 overlord
            - 15 roachwarren
            - 15 gas
            - 15 drone
            - 15 drone
            - 15 drone
            - 15 drone
            - 15 drone

    ZergMacro:
        # Build constant workers till x supply
        # Turning this off here for a bit more precision in build
        ConstantWorkerProductionTill: 0
        OpeningBuildOrder:
            - 12 overlord
            - 12 worker_scout:
                [nat, third, fourth, fifth, sixth, map_center, enemy_nat]
            - 12 drone
            - 13 drone
            - 14 drone
            - 15 drone
            - 16 hatchery
            - 15 spawningpool
            - 14 drone
            - 15 gas
            - 14 drone
            - 15 drone
            - 16 drone
            - 17 drone
            - 18 drone
            - 19 drone
            - 20 overlord
            - 19 drone
            - 20 evolutionchamber
            - 20 overlord
            - 20 drone
            - 20 drone
            - 20 overlord
            - 20 drone
            - 20 drone
            - 20 overlord
            - 20 drone
            - 20 drone
            - 20 drone
            - 20 overlord
            - 20 drone
            - 20 drone
            - 20 drone
            - 20 overlord
            - 20 drone
            - 20 drone
            - 20 overlord
            - 20 drone
            - 20 drone
            - 20 drone
            - 20 overlord
            - 20 drone
            - 20 drone
            - 20 overlord
            - 20 drone
            - 20 drone
            - 20 overlord

        

    SafeVsTerran:
        # Build constant workers till x supply
        # Turning this off here for a bit more precision in build
        ConstantWorkerProductionTill: 0
        OpeningBuildOrder:
            - 12 overlord
            - 12 worker_scout:
                [nat, third, fourth, fifth, sixth, map_center]
            - 12 drone
            - 13 drone
            - 13 drone
            - 13 spawningpool
            - 13 drone
            - 14 drone
            - 14 gas
            - 14 drone
            - 15 drone
            - 16 overlord
            - 16 drone
            - 16 drone
            - 17 drone
            - 20 drone
            - 21 drone
            - 22 drone
            - 23 drone
            - 19 drone





    HatcheryFirst:
        # Build constant workers till x supply
        # Turning this off here for a bit more precision in build
        ConstantWorkerProductionTill: 0
        OpeningBuildOrder:
            - 12 drone
            - 12 worker_scout:
                [nat, third, fourth, fifth, third, fourth, sixth, map_center]
            - 13 drone
            - 13 hatchery
            - 13 overlord
            - 13 drone
            - 13 spawningpool
            - 13 drone
            - 14 drone
            - 14 gas
            - 14 drone
            - 15 drone
            - 16 overlord
            - 16 drone
            - 16 drone
            - 17 drone
            - 20 drone
            - 21 drone
            - 22 drone
            - 23 drone
            - 19 drone
            - 20 evolutionchamber

    TwelvePool:
        # Build constant workers till x supply
        # Turning this off here for a bit more precision in build
        ConstantWorkerProductionTill: 0
        OpeningBuildOrder:
            - 12 spawningpool
            - 11 drone
            - 12 drone
            - 13 overlord
            - 13 drone


    OppeningVsLingRush:
        # Build constant workers till x supply
        # Turning this off here for a bit more precision in build
        ConstantWorkerProductionTill: 0
        OpeningBuildOrder:
            - 12 spawningpool
            - 11 drone
            - 12 drone
            - 13 overlord
            - 13 drone
            - 14 drone
            - 15 drone
            - 16 queen
            - 16 spinecrawler
            - 16 spinecrawler
            - 16 drone
            - 17 drone
            - 17 gas
            - 17 drone
            - 17 roachwarren
            - 17 queen


    AgressiveRoach:
        # Build constant workers till x supply
        # Turning this off here for a bit more precision in build
        ConstantWorkerProductionTill: 0
        OpeningBuildOrder:
            - 12 worker_scout
            - 12 drone
            - 13 drone
            - 14 spawningpool
            - 13 gas
            - 12 drone
            - 13 drone
            - 14 overlord
            - 14 drone
            - 15 roachwarren
            - 14 queen
            - 14 drone
            - 15 drone
            - 15 overlord
            - 15 hatchery


    Standard:
        # Build constant workers till x supply
        # Turning this off here for a bit more precision in build
        ConstantWorkerProductionTill: 0
        OpeningBuildOrder:
            - 12 worker_scout
            - 12 overlord
            - 12 drone
            - 13 drone
            - 14 drone
            - 15 drone
            - 13 hatchery
            - 14 drone
            - 14 spawningpool
            - 15 gas
            - 14 drone
            - 15 drone
            - 16 drone
            - 17 roachwarren
            - 16 zergling
            - 16 zergling


    PoolFirst:
        # Build constant workers till x supply
        # Turning this off here for a bit more precision in build
        ConstantWorkerProductionTill: 0
        OpeningBuildOrder:
            - 12 drone
            - 12 worker_scout:
                [nat, third, fourth, fifth, sixth, map_center]
            - 13 drone
            - 13 spawningpool
            - 13 overlord
            - 13 drone
            - 13 hatchery
            - 13 drone
            - 14 drone
            - 14 gas
            - 14 drone
            - 15 drone
            - 16 overlord
            - 16 drone
            - 16 drone
            - 17 drone
            - 20 drone
            - 16 overlord
            - 21 drone
            - 22 drone
            - 23 drone
            - 19 drone
            - 20 evolutionchamber

    OneOneRoaches:
        # Build constant workers till x supply
        # Turning this off here for a bit more precision in build
        ConstantWorkerProductionTill: 0
        OpeningBuildOrder:
            - 12 overlord
            - 12 drone
            - 13 drone
            - 14 drone
            - 15 drone
            - 15 hatchery
            - 15 drone
            - 15 spawningpool
            - 14 gas
            - 14 drone
            - 15 drone
            - 16 drone
            - 17 drone
            - 18 overlord
            - 18 drone
            - 19 queen
            - 20 roachwarren
            - 19 queen
            - 22 drone
            - 19 queen
            - 25 drone
            - 26 overlord
            - 25 gas
            - 25 drone
            - 26 drone
            - 27 drone
            - 28 drone
            - 29 drone
            - 30 drone
            - 31 drone
            - 35 overlord
            - 32 drone
            - 33 drone
            - 34 drone
            - 35 drone
            - 36 drone
            - 37 drone
            


    OppeningVsMarineRush:
        # Build constant workers till x supply
        # Turning this off here for a bit more precision in build
        ConstantWorkerProductionTill: 0
        OpeningBuildOrder:
            - 12 spawningpool
            - 11 drone
            - 12 drone
            - 13 overlord
            - 13 drone
            - 14 drone
            - 15 drone
            - 16 spinecrawler
            - 16 spinecrawler
            - 16 spinecrawler
            - 16 drone
            - 17 drone
            - 17 gas
            - 17 drone
            - 13 overlord
            - 17 roachwarren
            - 18 BURROW

    MacroVsTerran:
        # Build constant workers till x supply
        # Turning this off here for a bit more precision in build
        ConstantWorkerProductionTill: 0
        OpeningBuildOrder:
            - 12 overlord
            - 12 worker_scout:
                [nat, third, fourth, fifth, third, fourth, sixth, map_center]
            - 12 drone
            - 13 drone
            - 14 drone
            - 15 drone
            - 15 hatchery
            - 14 drone
            - 15 spawningpool
            - 14 gas
            - 14 drone
            - 15 drone
            - 16 drone
            - 17 drone
            - 18 overlord
            - 18 drone
            - 19 drone
            - 20 hatchery
            - 19 drone
            - 20 drone
            - 21 drone
            - 22 drone
            - 23 drone
            - 24 drone
            - 25 drone
            - 26 overlord
            - 26 drone
            - 27 drone
            - 28 drone
            - 29 drone
            - 30 drone
            - 31 drone
            - 32 drone
            - 33 drone
            - 34 overlord
            - 34 drone
            - 35 drone
            - 36 drone
            - 37 drone
            - 37 hatchery
            - 38 overlord
            - 38 drone
            - 39 drone
            - 40 overlord
            - 40 drone
            - 41 drone

